simple_scheduler/__init__.py
simple_scheduler/base.py
simple_scheduler/event.py
simple_scheduler/recurring.py
simple_scheduler-1.1.11.dist-info/LICENSE
simple_scheduler-1.1.11.dist-info/METADATA
simple_scheduler-1.1.11.dist-info/WHEEL
simple_scheduler-1.1.11.dist-info/top_level.txt
simple_scheduler-1.1.11.dist-info/RECORD
