Metadata-Version: 2.1
Name: simple-scheduler
Version: 1.1.11
Summary: Easily schedule multiple events and recurring tasks (simultaneously in background).
Home-page: https://github.com/Vernal-Inertia/simple_scheduler
Author: Vernal Inertia
Author-email: tanveer2407@gmail.com
License: MIT
Project-URL: Examples, https://github.com/Vernal-Inertia/simple_scheduler/tree/main/examples
Project-URL: Issues, https://github.com/Vernal-Inertia/simple_scheduler/issues
Project-URL: Documentation, https://github.com/Vernal-Inertia/simple_scheduler/blob/main/README.md
Project-URL: Source, https://github.com/Vernal-Inertia/simple_scheduler
Keywords: python,schedule,simple,scheduler,jobs,tasks,easy
Platform: UNKNOWN
Classifier: License :: OSI Approved :: MIT License
Classifier: Programming Language :: Python :: 3
Classifier: Development Status :: 3 - Alpha
Requires-Python: >=3
Requires-Dist: multiprocess
Requires-Dist: pytz
